aar_doc/__init__.py
aar_doc/cli.py
aar_doc/core.py
aar_doc/defaults.py
aar_doc/markdown.py
aar_doc/templates/markdown.j2
aar_doc-2.3.0.dist-info/LICENSE
aar_doc-2.3.0.dist-info/METADATA
aar_doc-2.3.0.dist-info/WHEEL
aar_doc-2.3.0.dist-info/entry_points.txt
aar_doc-2.3.0.dist-info/RECORD
