Metadata-Version: 2.3
Name: aar_doc
Version: 2.3.0
Summary: A tool for generating docs for Ansible roles
License: MIT
Author: Miika Kankare
Author-email: miika@kanka.re
Requires-Python: >=3.9,<4.0
Classifier: License :: OSI Approved :: MIT License
Classifier: Programming Language :: Python :: 3
Classifier: Programming Language :: Python :: 3.9
Classifier: Programming Language :: Python :: 3.10
Classifier: Programming Language :: Python :: 3.11
Classifier: Programming Language :: Python :: 3.12
Classifier: Programming Language :: Python :: 3.13
Requires-Dist: Jinja2 (>=3.1.2,<4.0.0)
Requires-Dist: click (>=8.1.3,<9.0.0)
Requires-Dist: ruamel-yaml (>=0.18.6,<0.19.0)
Requires-Dist: typer (>=0.16.0,<0.17.0)
Project-URL: Documentation, https://github.com/telekom-mms/aar_doc/
Project-URL: Homepage, https://github.com/telekom-mms/aar_doc/
Project-URL: Repository, https://github.com/telekom-mms/aar_doc/
